pulumi_ml/__init__.py
pulumi_ml/deployment.py
pulumi_ml-0.1.10.dist-info/LICENSE
pulumi_ml-0.1.10.dist-info/WHEEL
pulumi_ml-0.1.10.dist-info/METADATA
pulumi_ml-0.1.10.dist-info/RECORD
